archadeptcli/__init__.py
archadeptcli/__main__.py
archadeptcli/console.py
archadeptcli/diagram.py
archadeptcli/docker.py
archadeptcli/exceptions.py
archadeptcli/static/FiraCodeNerdFont-Regular/FiraCodeNerdFont-Regular.ttf
archadeptcli/static/FiraCodeNerdFont-Regular/LICENSE
archadeptcli/static/__init__.py
archadeptcli/static/instructions.json
archadeptcli-1.2.2.dist-info/LICENSE
archadeptcli-1.2.2.dist-info/METADATA
archadeptcli-1.2.2.dist-info/WHEEL
archadeptcli-1.2.2.dist-info/entry_points.txt
archadeptcli-1.2.2.dist-info/RECORD
