Metadata-Version: 2.1
Name: archadeptcli
Version: 1.2.2
Summary: Command line interface for building, running, debugging, and disassembling the ArchAdept training course example projects.
Home-page: https://archadept.com/
License: MIT
Author: Ash Wilding
Author-email: ash@archadept.com
Requires-Python: >=3.8,<4.0
Classifier: License :: OSI Approved :: MIT License
Classifier: Programming Language :: Python :: 3
Classifier: Programming Language :: Python :: 3.8
Classifier: Programming Language :: Python :: 3.9
Classifier: Programming Language :: Python :: 3.10
Classifier: Programming Language :: Python :: 3.11
Classifier: Programming Language :: Python :: 3.12
Requires-Dist: rich (>=13.7.0,<14.0.0)
Project-URL: Repository, https://github.com/archadept/archadeptcli
